thonny_tunisiaschools-0.0.14.data/data/requirements.txt
thonnycontrib/tunisiaschools/UIViewer.py
thonnycontrib/tunisiaschools/__init__.py
thonnycontrib/tunisiaschools/res/designer_16.png
thonnycontrib/tunisiaschools/res/qt_16.png
thonnycontrib/tunisiaschools/res/qt_32.png
thonny_tunisiaschools-0.0.14.dist-info/METADATA
thonny_tunisiaschools-0.0.14.dist-info/WHEEL
thonny_tunisiaschools-0.0.14.dist-info/top_level.txt
thonny_tunisiaschools-0.0.14.dist-info/RECORD
